{
    "national": {
        "2024": {
            "National": 400,
            "Eastern Cape": 25,
            "Free State": 10,
            "Gauteng": 47,
            "KwaZulu-Natal": 41,
            "Limpopo": 20,
            "Mpumalanga": 15,
            "North West": 13,
            "Northern Cape": 5,
            "Western Cape": 24
        },
        "2019": {
            "National": 400,
            "Eastern Cape": 25,
            "Free State": 11,
            "Gauteng": 48,
            "KwaZulu-Natal": 41,
            "Limpopo": 19,
            "Mpumalanga": 15,
            "North West": 13,
            "Northern Cape": 5,
            "Western Cape": 23
        },
        "2014": {
            "National": 400,
            "Eastern Cape": 26,
            "Free State": 11,
            "Gauteng": 48,
            "KwaZulu-Natal": 40,
            "Limpopo": 19,
            "Mpumalanga": 15,
            "North West": 13,
            "Northern Cape": 5,
            "Western Cape": 23
        },
        "2009": {
            "National": 400,
            "Eastern Cape": 26,
            "Free State": 12,
            "Gauteng": 47,
            "KwaZulu-Natal": 39,
            "Limpopo": 19,
            "Mpumalanga": 15,
            "North West": 14,
            "Northern Cape": 5,
            "Western Cape": 23
        }
    },
    "provincial": {
        "2024": {
            "Eastern Cape": 72,
            "Free State": 30,
            "Gauteng": 80,
            "KwaZulu-Natal": 80,
            "Limpopo": 64,
            "Mpumalanga": 51,
            "North West": 38,
            "Northern Cape": 30,
            "Western Cape": 42
        },
        "2019": {
            "Eastern Cape": 63,
            "Free State": 30,
            "Gauteng": 73,
            "KwaZulu-Natal": 80,
            "Limpopo": 49,
            "Mpumalanga": 30,
            "North West": 33,
            "Northern Cape": 30,
            "Western Cape": 42
        },
        "2014": {
            "Eastern Cape": 63,
            "Free State": 30,
            "Gauteng": 80,
            "KwaZulu-Natal": 80,
            "Limpopo": 49,
            "Mpumalanga": 30,
            "North West": 33,
            "Northern Cape": 30,
            "Western Cape": 42
        },
        "2009": {
            "Eastern Cape": 63,
            "Free State": 30,
            "Gauteng": 80,
            "KwaZulu-Natal": 80,
            "Limpopo": 49,
            "Mpumalanga": 30,
            "North West": 33,
            "Northern Cape": 30,
            "Western Cape": 42
        }
    }
}